calcu.py
calcu-1.0.0.dist-info/LICENSE
calcu-1.0.0.dist-info/METADATA
calcu-1.0.0.dist-info/WHEEL
calcu-1.0.0.dist-info/entry_points.txt
calcu-1.0.0.dist-info/top_level.txt
calcu-1.0.0.dist-info/zip-safe
calcu-1.0.0.dist-info/RECORD
